AUTHORS.rst
CONTRIBUTING.rst
HISTORY.rst
LICENSE
MANIFEST.in
README.rst
setup.py
django_mantis_stix_importer.egg-info/PKG-INFO
django_mantis_stix_importer.egg-info/SOURCES.txt
django_mantis_stix_importer.egg-info/dependency_links.txt
django_mantis_stix_importer.egg-info/not-zip-safe
django_mantis_stix_importer.egg-info/requires.txt
django_mantis_stix_importer.egg-info/top_level.txt
mantis_stix_importer/__init__.py
mantis_stix_importer/importer.py
mantis_stix_importer/models.py
mantis_stix_importer/management/__init__.py
mantis_stix_importer/management/commands/__init__.py
mantis_stix_importer/management/commands/mantis_stix_import.py
mantis_stix_importer/management/commands/mantis_stix_set_naming.py