Metadata-Version: 1.1
Name: django-mantis-stix-importer
Version: 0.2.0
Summary: A module implementing import of STIX and CybOX XML files for the Mantis Cyber Threat Intelligence Mgmt. Framework.
Home-page: https://github.com/siemens/django-mantis-stix-importer
Author: Siemens
Author-email: mantis.cert@siemens.com
License: GPLv2+
Keywords: django-mantis-stix-importer
Platform: UNKNOWN
Classifier: Development Status :: 3 - Alpha
Classifier: Framework :: Django
Classifier: Intended Audience :: Developers
Classifier: License :: OSI Approved :: GNU General Public License v2 or later (GPLv2+)
Classifier: Natural Language :: English
Classifier: Programming Language :: Python :: 2.7
Classifier: Topic :: Security
